pysurf96.libs/libquadmath-96973f99.so.0.0.0
pysurf96.libs/libgfortran-040039e1.so.5.0.0
pysurf96/wrapper.py
pysurf96/py.typed
pysurf96/CMakeLists.txt
pysurf96/surfdisp96.f
pysurf96/__init__.py
pysurf96/surfdisp96_ext.pypy310-pp73-x86_64-linux-gnu.so
pysurf96/surfdisp96_ext.pyi
pysurf96-1.0.1.dist-info/RECORD
pysurf96-1.0.1.dist-info/METADATA
pysurf96-1.0.1.dist-info/WHEEL
