Metadata-Version: 2.1
Name: pysurf96
Version: 1.0.1
Summary: Surface Wave Dispersion Python Wrapper for surf96.
Keywords: surface wave dispersion,surf96,dispersion curve,dispersion analysis
Author-Email: Marius Paul Isken <mi@gfz-potsdam.de>
Maintainer-Email: Marius Paul Isken <mi@gfz-potsdam.de>
Classifier: Intended Audience :: Science/Research
Classifier: Topic :: Scientific/Engineering
Classifier: Topic :: Scientific/Engineering :: Physics
Classifier: Programming Language :: Fortran
Classifier: Operating System :: POSIX
Classifier: Operating System :: MacOS
Project-URL: Home, https://pyrocko.org
Project-URL: Github, https://github.com/miili/pysurf96
Project-URL: Issues, https://github.com/miili/pysurf96/issues
Requires-Python: >=3.10
Requires-Dist: numpy>=1.23.0
Requires-Dist: pre-commit>=4.0.1; extra == "dev"
Requires-Dist: pytest>=8.3; extra == "dev"
Requires-Dist: ruff>=0.8.0; extra == "dev"
Provides-Extra: dev
